[
    {
        "trade_type": "SELL",
        "filter_text": "10k",
        "price": 737.0,
        "min_amount": 10000.0,
        "max_amount": 459335.25
    },
    {
        "trade_type": "SELL",
        "filter_text": "20k",
        "price": 740.05,
        "min_amount": 20000.0,
        "max_amount": 299875.66
    },
    {
        "trade_type": "SELL",
        "filter_text": "40k",
        "price": 740.31,
        "min_amount": 20000.0,
        "max_amount": 86942.0
    },
    {
        "trade_type": "SELL",
        "filter_text": "90k",
        "price": 740.5,
        "min_amount": 50000.0,
        "max_amount": 485108.95
    },
    {
        "trade_type": "SELL",
        "filter_text": "100k",
        "price": 740.5,
        "min_amount": 50000.0,
        "max_amount": 485108.95
    },
    {
        "trade_type": "BUY",
        "filter_text": "10k",
        "price": 742.97,
        "min_amount": 2000.0,
        "max_amount": 118022.95
    },
    {
        "trade_type": "BUY",
        "filter_text": "20k",
        "price": 742.97,
        "min_amount": 2000.0,
        "max_amount": 118022.95
    },
    {
        "trade_type": "BUY",
        "filter_text": "40k",
        "price": 742.97,
        "min_amount": 2000.0,
        "max_amount": 118022.95
    },
    {
        "trade_type": "BUY",
        "filter_text": "90k",
        "price": 743.0,
        "min_amount": 50000.0,
        "max_amount": 199447.39
    },
    {
        "trade_type": "BUY",
        "filter_text": "100k",
        "price": 743.0,
        "min_amount": 50000.0,
        "max_amount": 199447.39
    }
]